fish_hook-0.1.4.dist-info/DESCRIPTION.rst
fish_hook-0.1.4.dist-info/METADATA
fish_hook-0.1.4.dist-info/RECORD
fish_hook-0.1.4.dist-info/WHEEL
fish_hook-0.1.4.dist-info/entry_points.txt
fish_hook-0.1.4.dist-info/metadata.json
fish_hook-0.1.4.dist-info/top_level.txt
fishhook/__init__.py
fishhook/__main__.py
fishhook/app.py
fishhook/command.py
fishhook/fishhook.py
fishhook/handler.py
fishhook/server.py
fishhook/settings.py
fishhook/utils.py
