Metadata-Version: 2.0
Name: fish-hook
Version: 0.1.4
Summary: A console tool which manages your github webhooks efficiently.
Home-page: https://github.com/dcalsky/fish-hook/
Author: Dcalsky
Author-email: dcalsky@gmail.com
License: MIT
Platform: any
Classifier: Development Status :: 2 - Pre-Alpha
Classifier: License :: OSI Approved :: MIT License
Classifier: Programming Language :: Python
Classifier: Programming Language :: Python :: 3.5
Classifier: Programming Language :: Python :: 3.6
Classifier: Topic :: Software Development :: Build Tools
Requires-Dist: click (>=6.7)
Requires-Dist: colorama
Requires-Dist: sanic (>=0.3.1)
